{
    ":created_at": "2017-01-19T15:35:16.381Z",
    ":updated_at": "2017-01-30T12:31:24.639Z",
    ":version": "rv-6k47~dj9m_an2m",
    "address_1": "2800 Block GALE AV",
    "case_number": "170003653",
    "categorization": {
        "category": "property",
        "incident_type": "Theft of Vehicle",
        "sub_category": "vehicle"
    },
    "city": "LONG BEACH",
    "clearance_type": "",
    "created_at": "2017-01-19T10:34:31.000",
    "day_of_week": "Wednesday",
    "hour_of_day": "15",
    "incident_datetime": "2017-01-18T15:15:00.000",
    "incident_description": "GRAND THEFT; MOTOR VEHICLE",
    "incident_id": "789608744",
    "incident_type_primary": "Grand Theft Auto",
    "latitude": "33.808164",
    "location": {
        "coordinates": [
            -118.207511,
            33.808164
        ],
        "type": "Point"
    },
    "longitude": "-118.207511",
    "parent_incident_type": "Theft of Vehicle",
    "primary_key": "du6n-4fyc-row-9ip8_ujb8__bzwc",
    "state": "CA",
    "updated_at": "2017-01-30T12:31:20.000",
    "zip": "90810"
}